Metadata-Version: 2.1
Name: fastbooru
Version: 0.1.2
Summary: Because all other cli downloaders suck...
Home-page: https://github.com/cloud11665/fastbooru
Author: Cloud11665
Author-email: Cloud11665@protonmail.com
License: gnu GPL-3.0
Platform: UNKNOWN
Classifier: Programming Language :: Python :: 3.7
Classifier: Programming Language :: Python :: 3.8
Classifier: Programming Language :: Python :: 3.9
Classifier: Operating System :: OS Independent
Requires-Python: >=3.7
